import java.util.concurrent.BlockingQueue;

public final class adn
  extends Thread
{
  volatile boolean a = false;
  private final BlockingQueue b;
  private final adm c;
  private final adg d;
  private final aeb e;
  
  public adn(BlockingQueue paramBlockingQueue, adm paramadm, adg paramadg, aeb paramaeb)
  {
    this.b = paramBlockingQueue;
    this.c = paramadm;
    this.d = paramadg;
    this.e = paramaeb;
  }
  
  /* Error */
  public final void run()
  {
    // Byte code:
    //   0: bipush 10
    //   2: invokestatic 43	android/os/Process:setThreadPriority	(I)V
    //   5: invokestatic 49	android/os/SystemClock:elapsedRealtime	()J
    //   8: pop2
    //   9: aload_0
    //   10: getfield 23	adn:b	Ljava/util/concurrent/BlockingQueue;
    //   13: invokeinterface 55 1 0
    //   18: checkcast 57	ads
    //   21: astore_1
    //   22: aload_1
    //   23: ldc 59
    //   25: invokevirtual 62	ads:a	(Ljava/lang/String;)V
    //   28: aload_1
    //   29: getfield 65	ads:g	Z
    //   32: ifeq +43 -> 75
    //   35: aload_1
    //   36: ldc 67
    //   38: invokevirtual 69	ads:b	(Ljava/lang/String;)V
    //   41: goto -36 -> 5
    //   44: astore_2
    //   45: invokestatic 49	android/os/SystemClock:elapsedRealtime	()J
    //   48: pop2
    //   49: aload_2
    //   50: invokestatic 72	ads:a	(Laef;)Laef;
    //   53: astore_2
    //   54: aload_0
    //   55: getfield 29	adn:e	Laeb;
    //   58: aload_1
    //   59: aload_2
    //   60: invokevirtual 77	aeb:a	(Lads;Laef;)V
    //   63: goto -58 -> 5
    //   66: astore_1
    //   67: aload_0
    //   68: getfield 21	adn:a	Z
    //   71: ifeq -66 -> 5
    //   74: return
    //   75: getstatic 83	android/os/Build$VERSION:SDK_INT	I
    //   78: bipush 14
    //   80: if_icmplt +10 -> 90
    //   83: aload_1
    //   84: getfield 85	ads:c	I
    //   87: invokestatic 90	android/net/TrafficStats:setThreadStatsTag	(I)V
    //   90: aload_0
    //   91: getfield 25	adn:c	Ladm;
    //   94: aload_1
    //   95: invokeinterface 95 2 0
    //   100: astore_2
    //   101: aload_1
    //   102: ldc 97
    //   104: invokevirtual 62	ads:a	(Ljava/lang/String;)V
    //   107: aload_2
    //   108: getfield 101	adp:d	Z
    //   111: ifeq +62 -> 173
    //   114: aload_1
    //   115: getfield 104	ads:h	Z
    //   118: ifeq +55 -> 173
    //   121: aload_1
    //   122: ldc 106
    //   124: invokevirtual 69	ads:b	(Ljava/lang/String;)V
    //   127: goto -122 -> 5
    //   130: astore_2
    //   131: aload_2
    //   132: ldc 108
    //   134: iconst_1
    //   135: anewarray 110	java/lang/Object
    //   138: dup
    //   139: iconst_0
    //   140: aload_2
    //   141: invokevirtual 114	java/lang/Exception:toString	()Ljava/lang/String;
    //   144: aastore
    //   145: invokestatic 119	aeg:a	(Ljava/lang/Throwable;Ljava/lang/String;[Ljava/lang/Object;)V
    //   148: new 35	aef
    //   151: dup
    //   152: aload_2
    //   153: invokespecial 122	aef:<init>	(Ljava/lang/Throwable;)V
    //   156: astore_2
    //   157: invokestatic 49	android/os/SystemClock:elapsedRealtime	()J
    //   160: pop2
    //   161: aload_0
    //   162: getfield 29	adn:e	Laeb;
    //   165: aload_1
    //   166: aload_2
    //   167: invokevirtual 77	aeb:a	(Lads;Laef;)V
    //   170: goto -165 -> 5
    //   173: aload_1
    //   174: aload_2
    //   175: invokevirtual 125	ads:a	(Ladp;)Lady;
    //   178: astore_2
    //   179: aload_1
    //   180: ldc 127
    //   182: invokevirtual 62	ads:a	(Ljava/lang/String;)V
    //   185: aload_1
    //   186: getfield 130	ads:f	Z
    //   189: ifeq +33 -> 222
    //   192: aload_2
    //   193: getfield 135	ady:b	Ladh;
    //   196: ifnull +26 -> 222
    //   199: aload_0
    //   200: getfield 27	adn:d	Ladg;
    //   203: aload_1
    //   204: getfield 138	ads:b	Ljava/lang/String;
    //   207: aload_2
    //   208: getfield 135	ady:b	Ladh;
    //   211: invokeinterface 143 3 0
    //   216: aload_1
    //   217: ldc -111
    //   219: invokevirtual 62	ads:a	(Ljava/lang/String;)V
    //   222: aload_1
    //   223: iconst_1
    //   224: putfield 104	ads:h	Z
    //   227: aload_0
    //   228: getfield 29	adn:e	Laeb;
    //   231: aload_1
    //   232: aload_2
    //   233: invokevirtual 148	aeb:a	(Lads;Lady;)V
    //   236: goto -231 -> 5
    // Local variable table:
    //   start	length	slot	name	signature
    //   0	239	0	this	adn
    //   21	38	1	localads	ads
    //   66	166	1	localInterruptedException	InterruptedException
    //   44	6	2	localaef	aef
    //   53	55	2	localObject1	Object
    //   130	23	2	localException	Exception
    //   156	77	2	localObject2	Object
    // Exception table:
    //   from	to	target	type
    //   22	41	44	aef
    //   75	90	44	aef
    //   90	127	44	aef
    //   173	222	44	aef
    //   222	236	44	aef
    //   9	22	66	java/lang/InterruptedException
    //   22	41	130	java/lang/Exception
    //   75	90	130	java/lang/Exception
    //   90	127	130	java/lang/Exception
    //   173	222	130	java/lang/Exception
    //   222	236	130	java/lang/Exception
  }
}


/* Location:              C:\DEV\android\dex2jar-2.1-SNAPSHOT\classes-dex2jar.jar!\adn.class
 * Java compiler version: 6 (50.0)
 * JD-Core Version:       0.7.1
 */