public abstract class ddj
  implements dee
{
  private static final ddp a = ;
  
  /* Error */
  private dea a(byte[] paramArrayOfByte, int paramInt1, int paramInt2, ddp paramddp)
  {
    // Byte code:
    //   0: aload_1
    //   1: iload_2
    //   2: iload_3
    //   3: invokestatic 29	ddn:a	([BII)Lddn;
    //   6: astore_1
    //   7: aload_0
    //   8: aload_1
    //   9: aload 4
    //   11: invokevirtual 32	ddj:a	(Lddn;Lddp;)Ljava/lang/Object;
    //   14: checkcast 34	dea
    //   17: astore 4
    //   19: aload_1
    //   20: iconst_0
    //   21: invokevirtual 37	ddn:a	(I)V
    //   24: aload 4
    //   26: areturn
    //   27: astore_1
    //   28: aload_1
    //   29: aload 4
    //   31: putfield 40	ddx:a	Ldea;
    //   34: aload_1
    //   35: athrow
    //   36: astore_1
    //   37: aload_1
    //   38: athrow
    // Local variable table:
    //   start	length	slot	name	signature
    //   0	39	0	this	ddj
    //   0	39	1	paramArrayOfByte	byte[]
    //   0	39	2	paramInt1	int
    //   0	39	3	paramInt2	int
    //   0	39	4	paramddp	ddp
    // Exception table:
    //   from	to	target	type
    //   19	24	27	ddx
    //   0	19	36	ddx
    //   28	36	36	ddx
  }
}


/* Location:              C:\DEV\android\dex2jar-2.1-SNAPSHOT\classes-dex2jar.jar!\ddj.class
 * Java compiler version: 6 (50.0)
 * JD-Core Version:       0.7.1
 */