public final class dhs
{
  private final dfh a;
  private final dfi b;
  
  public dhs(dfh paramdfh, dfi paramdfi)
  {
    this.a = paramdfh;
    this.b = paramdfi;
  }
  
  /* Error */
  public static java.net.Socket a(int paramInt1, int paramInt2, dgf paramdgf)
  {
    // Byte code:
    //   0: invokestatic 26	dgn:a	()Ldgn;
    //   3: astore 4
    //   5: aload_2
    //   6: getfield 31	dgf:b	Ljava/net/Proxy;
    //   9: astore 5
    //   11: aload_2
    //   12: getfield 34	dgf:a	Ldez;
    //   15: astore_3
    //   16: aload 5
    //   18: invokevirtual 40	java/net/Proxy:type	()Ljava/net/Proxy$Type;
    //   21: getstatic 46	java/net/Proxy$Type:DIRECT	Ljava/net/Proxy$Type;
    //   24: if_acmpeq +14 -> 38
    //   27: aload 5
    //   29: invokevirtual 40	java/net/Proxy:type	()Ljava/net/Proxy$Type;
    //   32: getstatic 49	java/net/Proxy$Type:HTTP	Ljava/net/Proxy$Type;
    //   35: if_acmpne +29 -> 64
    //   38: aload_3
    //   39: getfield 55	dez:d	Ljavax/net/SocketFactory;
    //   42: invokevirtual 61	javax/net/SocketFactory:createSocket	()Ljava/net/Socket;
    //   45: astore_3
    //   46: aload_3
    //   47: iload_0
    //   48: invokevirtual 67	java/net/Socket:setSoTimeout	(I)V
    //   51: aload 4
    //   53: aload_3
    //   54: aload_2
    //   55: getfield 71	dgf:c	Ljava/net/InetSocketAddress;
    //   58: iload_1
    //   59: invokevirtual 74	dgn:a	(Ljava/net/Socket;Ljava/net/InetSocketAddress;I)V
    //   62: aload_3
    //   63: areturn
    //   64: new 63	java/net/Socket
    //   67: dup
    //   68: aload 5
    //   70: invokespecial 77	java/net/Socket:<init>	(Ljava/net/Proxy;)V
    //   73: astore_3
    //   74: goto -28 -> 46
    //   77: astore_2
    //   78: new 79	dhq
    //   81: dup
    //   82: aload_2
    //   83: invokespecial 82	dhq:<init>	(Ljava/io/IOException;)V
    //   86: athrow
    // Local variable table:
    //   start	length	slot	name	signature
    //   0	87	0	paramInt1	int
    //   0	87	1	paramInt2	int
    //   0	87	2	paramdgf	dgf
    //   15	59	3	localObject	Object
    //   3	49	4	localdgn	dgn
    //   9	60	5	localProxy	java.net.Proxy
    // Exception table:
    //   from	to	target	type
    //   5	38	77	java/io/IOException
    //   38	46	77	java/io/IOException
    //   46	62	77	java/io/IOException
    //   64	74	77	java/io/IOException
  }
  
  /* Error */
  public final dht a(int paramInt1, int paramInt2, int paramInt3, dfy paramdfy, dgf paramdgf, java.util.List paramList, boolean paramBoolean)
  {
    // Byte code:
    //   0: aload 5
    //   2: getfield 34	dgf:a	Ldez;
    //   5: astore 11
    //   7: new 89	dgh
    //   10: dup
    //   11: aload 6
    //   13: invokespecial 92	dgh:<init>	(Ljava/util/List;)V
    //   16: astore 12
    //   18: aconst_null
    //   19: astore 6
    //   21: iload_2
    //   22: iload_1
    //   23: aload 5
    //   25: invokestatic 94	dhs:a	(IILdgf;)Ljava/net/Socket;
    //   28: astore 13
    //   30: aload 5
    //   32: getfield 34	dgf:a	Ldez;
    //   35: getfield 98	dez:e	Ljavax/net/ssl/SSLSocketFactory;
    //   38: ifnull +412 -> 450
    //   41: aload 5
    //   43: getfield 31	dgf:b	Ljava/net/Proxy;
    //   46: invokevirtual 40	java/net/Proxy:type	()Ljava/net/Proxy$Type;
    //   49: getstatic 49	java/net/Proxy$Type:HTTP	Ljava/net/Proxy$Type;
    //   52: if_acmpne +398 -> 450
    //   55: iconst_1
    //   56: istore 17
    //   58: iload 17
    //   60: ifeq +508 -> 568
    //   63: aload 4
    //   65: invokevirtual 103	dfy:a	()Ljava/net/URL;
    //   68: invokevirtual 109	java/net/URL:getHost	()Ljava/lang/String;
    //   71: astore 9
    //   73: aload 4
    //   75: invokevirtual 103	dfy:a	()Ljava/net/URL;
    //   78: invokestatic 114	dgs:a	(Ljava/net/URL;)I
    //   81: istore 17
    //   83: iload 17
    //   85: ldc 116
    //   87: invokestatic 119	dgs:a	(Ljava/lang/String;)I
    //   90: if_icmpne +366 -> 456
    //   93: aload 9
    //   95: astore 8
    //   97: new 121	dfz
    //   100: astore 14
    //   102: aload 14
    //   104: invokespecial 122	dfz:<init>	()V
    //   107: new 105	java/net/URL
    //   110: astore 10
    //   112: aload 10
    //   114: ldc 116
    //   116: aload 9
    //   118: iload 17
    //   120: ldc 124
    //   122: invokespecial 127	java/net/URL:<init>	(Ljava/lang/String;Ljava/lang/String;ILjava/lang/String;)V
    //   125: aload 14
    //   127: aload 10
    //   129: invokevirtual 130	dfz:a	(Ljava/net/URL;)Ldfz;
    //   132: ldc -124
    //   134: aload 8
    //   136: invokevirtual 135	dfz:a	(Ljava/lang/String;Ljava/lang/String;)Ldfz;
    //   139: ldc -119
    //   141: ldc -117
    //   143: invokevirtual 135	dfz:a	(Ljava/lang/String;Ljava/lang/String;)Ldfz;
    //   146: astore 8
    //   148: aload 4
    //   150: ldc -115
    //   152: invokevirtual 144	dfy:a	(Ljava/lang/String;)Ljava/lang/String;
    //   155: astore 9
    //   157: aload 9
    //   159: ifnull +13 -> 172
    //   162: aload 8
    //   164: ldc -115
    //   166: aload 9
    //   168: invokevirtual 135	dfz:a	(Ljava/lang/String;Ljava/lang/String;)Ldfz;
    //   171: pop
    //   172: aload 4
    //   174: ldc -110
    //   176: invokevirtual 144	dfy:a	(Ljava/lang/String;)Ljava/lang/String;
    //   179: astore 9
    //   181: aload 9
    //   183: ifnull +13 -> 196
    //   186: aload 8
    //   188: ldc -110
    //   190: aload 9
    //   192: invokevirtual 135	dfz:a	(Ljava/lang/String;Ljava/lang/String;)Ldfz;
    //   195: pop
    //   196: aload 8
    //   198: invokevirtual 149	dfz:a	()Ldfy;
    //   201: astore 8
    //   203: new 151	dgx
    //   206: astore 10
    //   208: aload 10
    //   210: aload_0
    //   211: getfield 17	dhs:b	Ldfi;
    //   214: aload_0
    //   215: getfield 15	dhs:a	Ldfh;
    //   218: aload 13
    //   220: invokespecial 154	dgx:<init>	(Ldfi;Ldfh;Ljava/net/Socket;)V
    //   223: aload 10
    //   225: iload_2
    //   226: iload_3
    //   227: invokevirtual 157	dgx:a	(II)V
    //   230: aload 8
    //   232: invokevirtual 103	dfy:a	()Ljava/net/URL;
    //   235: astore 14
    //   237: new 159	java/lang/StringBuilder
    //   240: astore 9
    //   242: aload 9
    //   244: ldc -95
    //   246: invokespecial 164	java/lang/StringBuilder:<init>	(Ljava/lang/String;)V
    //   249: aload 9
    //   251: aload 14
    //   253: invokevirtual 109	java/net/URL:getHost	()Ljava/lang/String;
    //   256: invokevirtual 168	java/lang/StringBuilder:append	(Ljava/lang/String;)Ljava/lang/StringBuilder;
    //   259: ldc -86
    //   261: invokevirtual 168	java/lang/StringBuilder:append	(Ljava/lang/String;)Ljava/lang/StringBuilder;
    //   264: aload 14
    //   266: invokestatic 114	dgs:a	(Ljava/net/URL;)I
    //   269: invokevirtual 173	java/lang/StringBuilder:append	(I)Ljava/lang/StringBuilder;
    //   272: ldc -81
    //   274: invokevirtual 168	java/lang/StringBuilder:append	(Ljava/lang/String;)Ljava/lang/StringBuilder;
    //   277: invokevirtual 178	java/lang/StringBuilder:toString	()Ljava/lang/String;
    //   280: astore 14
    //   282: aload 10
    //   284: aload 8
    //   286: getfield 181	dfy:c	Ldfo;
    //   289: aload 14
    //   291: invokevirtual 184	dgx:a	(Ldfo;Ljava/lang/String;)V
    //   294: aload 10
    //   296: invokevirtual 186	dgx:a	()V
    //   299: aload 10
    //   301: invokevirtual 189	dgx:c	()Ldgd;
    //   304: astore 9
    //   306: aload 9
    //   308: aload 8
    //   310: putfield 194	dgd:a	Ldfy;
    //   313: aload 9
    //   315: invokevirtual 197	dgd:a	()Ldgc;
    //   318: astore 8
    //   320: aload 8
    //   322: invokestatic 202	dhl:a	(Ldgc;)J
    //   325: lstore 20
    //   327: lload 20
    //   329: lstore 18
    //   331: lload 20
    //   333: ldc2_w 203
    //   336: lcmp
    //   337: ifne +6 -> 343
    //   340: lconst_0
    //   341: lstore 18
    //   343: aload 10
    //   345: lload 18
    //   347: invokevirtual 207	dgx:a	(J)Ldkv;
    //   350: astore 9
    //   352: aload 9
    //   354: ldc -48
    //   356: getstatic 214	java/util/concurrent/TimeUnit:MILLISECONDS	Ljava/util/concurrent/TimeUnit;
    //   359: invokestatic 217	dgs:b	(Ldkv;ILjava/util/concurrent/TimeUnit;)Z
    //   362: pop
    //   363: aload 9
    //   365: invokeinterface 222 1 0
    //   370: aload 8
    //   372: getfield 227	dgc:c	I
    //   375: lookupswitch	default:+25->400, 200:+116->491, 407:+149->524
    //   400: new 21	java/io/IOException
    //   403: astore 4
    //   405: new 159	java/lang/StringBuilder
    //   408: astore 5
    //   410: aload 5
    //   412: ldc -27
    //   414: invokespecial 164	java/lang/StringBuilder:<init>	(Ljava/lang/String;)V
    //   417: aload 4
    //   419: aload 5
    //   421: aload 8
    //   423: getfield 227	dgc:c	I
    //   426: invokevirtual 173	java/lang/StringBuilder:append	(I)Ljava/lang/StringBuilder;
    //   429: invokevirtual 178	java/lang/StringBuilder:toString	()Ljava/lang/String;
    //   432: invokespecial 230	java/io/IOException:<init>	(Ljava/lang/String;)V
    //   435: aload 4
    //   437: athrow
    //   438: astore 4
    //   440: new 79	dhq
    //   443: dup
    //   444: aload 4
    //   446: invokespecial 82	dhq:<init>	(Ljava/io/IOException;)V
    //   449: athrow
    //   450: iconst_0
    //   451: istore 17
    //   453: goto -395 -> 58
    //   456: new 159	java/lang/StringBuilder
    //   459: astore 8
    //   461: aload 8
    //   463: invokespecial 231	java/lang/StringBuilder:<init>	()V
    //   466: aload 8
    //   468: aload 9
    //   470: invokevirtual 168	java/lang/StringBuilder:append	(Ljava/lang/String;)Ljava/lang/StringBuilder;
    //   473: ldc -86
    //   475: invokevirtual 168	java/lang/StringBuilder:append	(Ljava/lang/String;)Ljava/lang/StringBuilder;
    //   478: iload 17
    //   480: invokevirtual 173	java/lang/StringBuilder:append	(I)Ljava/lang/StringBuilder;
    //   483: invokevirtual 178	java/lang/StringBuilder:toString	()Ljava/lang/String;
    //   486: astore 8
    //   488: goto -391 -> 97
    //   491: aload 10
    //   493: getfield 234	dgx:c	Ldkd;
    //   496: invokeinterface 239 1 0
    //   501: getfield 244	djz:b	J
    //   504: lconst_0
    //   505: lcmp
    //   506: ifle +62 -> 568
    //   509: new 21	java/io/IOException
    //   512: astore 4
    //   514: aload 4
    //   516: ldc -10
    //   518: invokespecial 230	java/io/IOException:<init>	(Ljava/lang/String;)V
    //   521: aload 4
    //   523: athrow
    //   524: aload 5
    //   526: getfield 34	dgf:a	Ldez;
    //   529: getfield 250	dez:h	Ldfa;
    //   532: aload 8
    //   534: aload 5
    //   536: getfield 31	dgf:b	Ljava/net/Proxy;
    //   539: invokestatic 253	dhl:a	(Ldfa;Ldgc;Ljava/net/Proxy;)Ldfy;
    //   542: astore 9
    //   544: aload 9
    //   546: astore 8
    //   548: aload 9
    //   550: ifnonnull -268 -> 282
    //   553: new 21	java/io/IOException
    //   556: astore 4
    //   558: aload 4
    //   560: ldc -1
    //   562: invokespecial 230	java/io/IOException:<init>	(Ljava/lang/String;)V
    //   565: aload 4
    //   567: athrow
    //   568: aload 11
    //   570: getfield 98	dez:e	Ljavax/net/ssl/SSLSocketFactory;
    //   573: aload 13
    //   575: aload 11
    //   577: getfield 258	dez:b	Ljava/lang/String;
    //   580: aload 11
    //   582: getfield 259	dez:c	I
    //   585: iconst_1
    //   586: invokevirtual 264	javax/net/ssl/SSLSocketFactory:createSocket	(Ljava/net/Socket;Ljava/lang/String;IZ)Ljava/net/Socket;
    //   589: checkcast 266	javax/net/ssl/SSLSocket
    //   592: astore 9
    //   594: aload 12
    //   596: aload 9
    //   598: invokevirtual 269	dgh:a	(Ljavax/net/ssl/SSLSocket;)Ldfk;
    //   601: astore 16
    //   603: invokestatic 26	dgn:a	()Ldgn;
    //   606: astore 14
    //   608: aconst_null
    //   609: astore 10
    //   611: aload 16
    //   613: getfield 275	dfk:g	Z
    //   616: ifeq +20 -> 636
    //   619: aload 14
    //   621: aload 9
    //   623: aload 11
    //   625: getfield 258	dez:b	Ljava/lang/String;
    //   628: aload 11
    //   630: getfield 279	dez:i	Ljava/util/List;
    //   633: invokevirtual 282	dgn:a	(Ljavax/net/ssl/SSLSocket;Ljava/lang/String;Ljava/util/List;)V
    //   636: aload 9
    //   638: invokevirtual 285	javax/net/ssl/SSLSocket:startHandshake	()V
    //   641: aload 9
    //   643: invokevirtual 289	javax/net/ssl/SSLSocket:getSession	()Ljavax/net/ssl/SSLSession;
    //   646: invokestatic 294	dfn:a	(Ljavax/net/ssl/SSLSession;)Ldfn;
    //   649: astore 15
    //   651: aload 10
    //   653: astore 8
    //   655: aload 16
    //   657: getfield 275	dfk:g	Z
    //   660: ifeq +28 -> 688
    //   663: aload 14
    //   665: aload 9
    //   667: invokevirtual 297	dgn:b	(Ljavax/net/ssl/SSLSocket;)Ljava/lang/String;
    //   670: astore 16
    //   672: aload 10
    //   674: astore 8
    //   676: aload 16
    //   678: ifnull +10 -> 688
    //   681: aload 16
    //   683: invokestatic 302	dfx:a	(Ljava/lang/String;)Ldfx;
    //   686: astore 8
    //   688: aload 14
    //   690: aload 9
    //   692: invokevirtual 305	dgn:a	(Ljavax/net/ssl/SSLSocket;)V
    //   695: aload 11
    //   697: getfield 309	dez:f	Ljavax/net/ssl/HostnameVerifier;
    //   700: aload 11
    //   702: getfield 258	dez:b	Ljava/lang/String;
    //   705: aload 9
    //   707: invokevirtual 289	javax/net/ssl/SSLSocket:getSession	()Ljavax/net/ssl/SSLSession;
    //   710: invokeinterface 315 3 0
    //   715: ifne +243 -> 958
    //   718: aload 9
    //   720: invokevirtual 289	javax/net/ssl/SSLSocket:getSession	()Ljavax/net/ssl/SSLSession;
    //   723: invokeinterface 321 1 0
    //   728: iconst_0
    //   729: aaload
    //   730: checkcast 323	java/security/cert/X509Certificate
    //   733: astore 14
    //   735: new 325	javax/net/ssl/SSLPeerUnverifiedException
    //   738: astore 8
    //   740: new 159	java/lang/StringBuilder
    //   743: astore 10
    //   745: aload 10
    //   747: ldc_w 327
    //   750: invokespecial 164	java/lang/StringBuilder:<init>	(Ljava/lang/String;)V
    //   753: aload 8
    //   755: aload 10
    //   757: aload 11
    //   759: getfield 258	dez:b	Ljava/lang/String;
    //   762: invokevirtual 168	java/lang/StringBuilder:append	(Ljava/lang/String;)Ljava/lang/StringBuilder;
    //   765: ldc_w 329
    //   768: invokevirtual 168	java/lang/StringBuilder:append	(Ljava/lang/String;)Ljava/lang/StringBuilder;
    //   771: aload 14
    //   773: invokestatic 334	dfd:a	(Ljava/security/cert/Certificate;)Ljava/lang/String;
    //   776: invokevirtual 168	java/lang/StringBuilder:append	(Ljava/lang/String;)Ljava/lang/StringBuilder;
    //   779: ldc_w 336
    //   782: invokevirtual 168	java/lang/StringBuilder:append	(Ljava/lang/String;)Ljava/lang/StringBuilder;
    //   785: aload 14
    //   787: invokevirtual 340	java/security/cert/X509Certificate:getSubjectDN	()Ljava/security/Principal;
    //   790: invokeinterface 345 1 0
    //   795: invokevirtual 168	java/lang/StringBuilder:append	(Ljava/lang/String;)Ljava/lang/StringBuilder;
    //   798: ldc_w 347
    //   801: invokevirtual 168	java/lang/StringBuilder:append	(Ljava/lang/String;)Ljava/lang/StringBuilder;
    //   804: aload 14
    //   806: invokestatic 352	djt:a	(Ljava/security/cert/X509Certificate;)Ljava/util/List;
    //   809: invokevirtual 355	java/lang/StringBuilder:append	(Ljava/lang/Object;)Ljava/lang/StringBuilder;
    //   812: invokevirtual 178	java/lang/StringBuilder:toString	()Ljava/lang/String;
    //   815: invokespecial 356	javax/net/ssl/SSLPeerUnverifiedException:<init>	(Ljava/lang/String;)V
    //   818: aload 8
    //   820: athrow
    //   821: astore 8
    //   823: iload 7
    //   825: ifeq +177 -> 1002
    //   828: aload 12
    //   830: iconst_1
    //   831: putfield 358	dgh:b	Z
    //   834: aload 8
    //   836: instanceof 360
    //   839: ifne +157 -> 996
    //   842: aload 8
    //   844: instanceof 362
    //   847: ifne +149 -> 996
    //   850: aload 8
    //   852: instanceof 364
    //   855: ifeq +14 -> 869
    //   858: aload 8
    //   860: invokevirtual 368	java/io/IOException:getCause	()Ljava/lang/Throwable;
    //   863: instanceof 370
    //   866: ifne +130 -> 996
    //   869: aload 8
    //   871: instanceof 325
    //   874: ifne +122 -> 996
    //   877: aload 8
    //   879: instanceof 364
    //   882: ifne +11 -> 893
    //   885: aload 8
    //   887: instanceof 372
    //   890: ifeq +106 -> 996
    //   893: aload 12
    //   895: getfield 374	dgh:a	Z
    //   898: ifeq +98 -> 996
    //   901: iconst_1
    //   902: istore 17
    //   904: iload 17
    //   906: ifeq +96 -> 1002
    //   909: iconst_1
    //   910: istore 17
    //   912: aload 9
    //   914: invokestatic 377	dgs:a	(Ljava/net/Socket;)V
    //   917: aload 13
    //   919: invokestatic 377	dgs:a	(Ljava/net/Socket;)V
    //   922: aload 6
    //   924: ifnonnull +84 -> 1008
    //   927: new 79	dhq
    //   930: dup
    //   931: aload 8
    //   933: invokespecial 82	dhq:<init>	(Ljava/io/IOException;)V
    //   936: astore 6
    //   938: iload 17
    //   940: ifne +109 -> 1049
    //   943: aload 6
    //   945: athrow
    //   946: astore 8
    //   948: aload 14
    //   950: aload 9
    //   952: invokevirtual 305	dgn:a	(Ljavax/net/ssl/SSLSocket;)V
    //   955: aload 8
    //   957: athrow
    //   958: aload 11
    //   960: getfield 380	dez:g	Ldfd;
    //   963: aload 11
    //   965: getfield 258	dez:b	Ljava/lang/String;
    //   968: aload 15
    //   970: getfield 382	dfn:b	Ljava/util/List;
    //   973: invokevirtual 385	dfd:a	(Ljava/lang/String;Ljava/util/List;)V
    //   976: new 387	dht
    //   979: dup
    //   980: aload 5
    //   982: aload 9
    //   984: aload 8
    //   986: aload 15
    //   988: invokespecial 390	dht:<init>	(Ldgf;Ljavax/net/ssl/SSLSocket;Ldfx;Ldfn;)V
    //   991: astore 8
    //   993: aload 8
    //   995: areturn
    //   996: iconst_0
    //   997: istore 17
    //   999: goto -95 -> 904
    //   1002: iconst_0
    //   1003: istore 17
    //   1005: goto -93 -> 912
    //   1008: aload 6
    //   1010: getfield 393	dhq:b	Ljava/io/IOException;
    //   1013: astore 9
    //   1015: getstatic 396	dhq:a	Ljava/lang/reflect/Method;
    //   1018: ifnull +21 -> 1039
    //   1021: getstatic 396	dhq:a	Ljava/lang/reflect/Method;
    //   1024: aload 8
    //   1026: iconst_1
    //   1027: anewarray 4	java/lang/Object
    //   1030: dup
    //   1031: iconst_0
    //   1032: aload 9
    //   1034: aastore
    //   1035: invokevirtual 402	java/lang/reflect/Method:invoke	(Ljava/lang/Object;[Ljava/lang/Object;)Ljava/lang/Object;
    //   1038: pop
    //   1039: aload 6
    //   1041: aload 8
    //   1043: putfield 393	dhq:b	Ljava/io/IOException;
    //   1046: goto -108 -> 938
    //   1049: goto -1028 -> 21
    //   1052: astore 9
    //   1054: goto -15 -> 1039
    //   1057: astore 9
    //   1059: goto -20 -> 1039
    //   1062: astore 8
    //   1064: aconst_null
    //   1065: astore 9
    //   1067: goto -244 -> 823
    // Local variable table:
    //   start	length	slot	name	signature
    //   0	1070	0	this	dhs
    //   0	1070	1	paramInt1	int
    //   0	1070	2	paramInt2	int
    //   0	1070	3	paramInt3	int
    //   0	1070	4	paramdfy	dfy
    //   0	1070	5	paramdgf	dgf
    //   0	1070	6	paramList	java.util.List
    //   0	1070	7	paramBoolean	boolean
    //   95	724	8	localObject1	Object
    //   821	111	8	localIOException1	java.io.IOException
    //   946	39	8	localdfx	dfx
    //   991	51	8	localdht	dht
    //   1062	1	8	localIOException2	java.io.IOException
    //   71	962	9	localObject2	Object
    //   1052	1	9	localIllegalAccessException	IllegalAccessException
    //   1057	1	9	localInvocationTargetException	java.lang.reflect.InvocationTargetException
    //   1065	1	9	localObject3	Object
    //   110	646	10	localObject4	Object
    //   5	959	11	localdez	dez
    //   16	878	12	localdgh	dgh
    //   28	890	13	localSocket	java.net.Socket
    //   100	849	14	localObject5	Object
    //   649	338	15	localdfn	dfn
    //   601	81	16	localObject6	Object
    //   56	948	17	i	int
    //   329	17	18	l1	long
    //   325	7	20	l2	long
    // Exception table:
    //   from	to	target	type
    //   63	93	438	java/io/IOException
    //   97	157	438	java/io/IOException
    //   162	172	438	java/io/IOException
    //   172	181	438	java/io/IOException
    //   186	196	438	java/io/IOException
    //   196	282	438	java/io/IOException
    //   282	327	438	java/io/IOException
    //   343	400	438	java/io/IOException
    //   400	438	438	java/io/IOException
    //   456	488	438	java/io/IOException
    //   491	524	438	java/io/IOException
    //   524	544	438	java/io/IOException
    //   553	568	438	java/io/IOException
    //   594	608	821	java/io/IOException
    //   688	821	821	java/io/IOException
    //   948	958	821	java/io/IOException
    //   958	993	821	java/io/IOException
    //   611	636	946	finally
    //   636	651	946	finally
    //   655	672	946	finally
    //   681	688	946	finally
    //   1021	1039	1052	java/lang/IllegalAccessException
    //   1021	1039	1057	java/lang/reflect/InvocationTargetException
    //   568	594	1062	java/io/IOException
  }
}


/* Location:              C:\DEV\android\dex2jar-2.1-SNAPSHOT\classes-dex2jar.jar!\dhs.class
 * Java compiler version: 6 (50.0)
 * JD-Core Version:       0.7.1
 */